vcfzap/__init__.py
vcfzap/vcfzap.py
vcfzap-1.2.0.dist-info/licenses/LICENSE
vcfzap-1.2.0.dist-info/METADATA
vcfzap-1.2.0.dist-info/WHEEL
vcfzap-1.2.0.dist-info/entry_points.txt
vcfzap-1.2.0.dist-info/top_level.txt
vcfzap-1.2.0.dist-info/RECORD
