Metadata-Version: 2.4
Name: vcfzap
Version: 1.2.0
Summary: A lightning-fast VCF contact extractor to CSV, TXT, JSON, HTML, SQLite, or terminal preview
Author-email: Mallik Mohammad Musaddiq <mallikmusaddiq1@gmail.com>
License: MIT License
Project-URL: Homepage, https://github.com/mallikmusaddiq1/vcfzap
Project-URL: Bug Tracker, https://github.com/mallikmusaddiq1/vcfzap/issues
Project-URL: Documentation, https://github.com/mallikmusaddiq1/vcfzap/tree/master/docs
Keywords: vcf,contact,extractor,csv,json,txt,html,sqlite
Classifier: Programming Language :: Python :: 3
Classifier: License :: OSI Approved :: MIT License
Classifier: Operating System :: OS Independent
Classifier: Intended Audience :: End Users/Desktop
Classifier: Topic :: Utilities
Requires-Python: >=3.6
License-File: LICENSE
Requires-Dist: vobject
Requires-Dist: chardet
Requires-Dist: tqdm
Requires-Dist: colorama
Dynamic: license-file
